{
  "maps": [
    {
      "id": "tanglewood",
      "type": "Small",
      "name": "Tanglewood Street House",
      "recommendedTeamSize": "1",
      "recommendedItems": "None",
      "description": "A small, three bedroom, single floor house with a basement."
    },
    {
      "id:": "edgefield",
      "type": "Small",
      "name": "Edgefield Street House",
      "recommendedTeamSize": "2",
      "recommendedItems": "Thermometer",
      "description": "A two story, six bedroom house with a basement."
    },
    {
      "id:": "ridgeview",
      "type": "Small",
      "name": "Ridgeview Road House",
      "recommendedTeamSize": "2",
      "recommendedItems": "Thermometer",
      "description": "A two story, four bedroom house with a basement."
    },
    {
      "id:": "grafton",
      "type": "Small",
      "name": "Grafton Farmhouse",
      "recommendedTeamSize": "2",
      "recommendedItems": "Thermometer",
      "description": "A two story, 4 bedroom farmhouse."
    },
    {
      "id:": "bleasdale",
      "type": "Small",
      "name": "Bleasdale Farmhouse",
      "recommendedTeamSize": "2",
      "recommendedItems": "Thermometer",
      "description": "A two story, 3 bedroom farmhouse with an Attic."
    },
    {
      "id:": "highschool",
      "type": "Medium",
      "name": "Brownstone High School",
      "recommendedTeamSize": "3",
      "recommendedItems": "Sanity Pills",
      "description": "Shut down due to unnatural deaths, this isolated School has been abandoned for decades."
    },
    {
      "id:": "prison",
      "type": "Medium",
      "name": "Prison",
      "recommendedTeamSize": "3",
      "recommendedItems": "Sanity Pills",
      "description": "The Prison was recently closed due to some unexplained deaths."
    },
    {
      "id:": "asylum",
      "type": "Large",
      "name": "Asylum",
      "recommendedTeamSize": "4",
      "recommendedItems": "Sanity Pills",
      "description": "This Asylum has been abandoned for years. Its only occupants are the paranormal."
    }
  ]
}
